iflow_mcp_piebro_vlc_mcp_server-0.1.10.dist-info/licenses/LICENSE
vlc_mcp_player/__init__.py
vlc_mcp_player/main.py
iflow_mcp_piebro_vlc_mcp_server-0.1.10.dist-info/METADATA
iflow_mcp_piebro_vlc_mcp_server-0.1.10.dist-info/WHEEL
iflow_mcp_piebro_vlc_mcp_server-0.1.10.dist-info/entry_points.txt
iflow_mcp_piebro_vlc_mcp_server-0.1.10.dist-info/top_level.txt
iflow_mcp_piebro_vlc_mcp_server-0.1.10.dist-info/RECORD
