Metadata-Version: 2.4
Name: iflow-mcp_piebro_vlc-mcp-server
Version: 0.1.10
Summary: An MCP (Model Contex Protocol) Server to play and control movies using VLC.
Author-email: Piet Brömmel <piet.broemmel@gmail.com>
License-Expression: MIT
Project-URL: Homepage, https://github.com/piebro/vlc-mcp-server
Project-URL: Bug Tracker, https://github.com/piebro/vlc-mcp-server/issues
Keywords: mcp,server,vlc
Classifier: Development Status :: 4 - Beta
Classifier: Intended Audience :: Developers
Classifier: Programming Language :: Python :: 3
Classifier: Programming Language :: Python :: 3.10
Requires-Python: >=3.10
License-File: LICENSE
Requires-Dist: mcp
Requires-Dist: requests
Provides-Extra: dev
Requires-Dist: ruff; extra == "dev"
Requires-Dist: pre-commit; extra == "dev"
Dynamic: license-file
